[
  {
    "__type": "TrafficIncident:http://schemas.microsoft.com/search/local/ws/rest/v1",
    "point": {
      "type": "Point",
      "coordinates": [
        40.159215,
        9.195036
      ]
    },
    "description": "SS128 Centrale Sarda tratto chiuso causa veicolo fermo da Gavoi a Sarule",
    "end": "/Date(1607027877329)/",
    "icon": 1,
    "incidentId": 9288751678406000,
    "isEndTimeBackfilled": true,
    "lastModified": "/Date(1606992515752)/",
    "roadClosed": true,
    "severity": 4,
    "source": 5,
    "start": "/Date(1606972740000)/",
    "title": "Via Carlo Felice NB",
    "toPoint": {
      "type": "Point",
      "coordinates": [
        40.160603,
        9.194988
      ]
    },
    "type": 3,
    "verified": true
  },
  {
    "__type": "TrafficIncident:http://schemas.microsoft.com/search/local/ws/rest/v1",
    "point": {
      "type": "Point",
      "coordinates": [
        40.160603,
        9.194988
      ]
    },
    "description": "SS128 Centrale Sarda tratto chiuso causa veicolo fermo da Gavoi a Sarule",
    "end": "/Date(1607027877329)/",
    "icon": 1,
    "incidentId": 9288751652806000,
    "isEndTimeBackfilled": true,
    "lastModified": "/Date(1606992515752)/",
    "roadClosed": true,
    "severity": 4,
    "source": 5,
    "start": "/Date(1606972740000)/",
    "title": "Via Sassari NB",
    "toPoint": {
      "type": "Point",
      "coordinates": [
        40.161898,
        9.195559
      ]
    },
    "type": 3,
    "verified": true
  },
  {
    "__type": "TrafficIncident:http://schemas.microsoft.com/search/local/ws/rest/v1",
    "point": {
      "type": "Point",
      "coordinates": [
        40.161879,
        9.195684
      ]
    },
    "description": "SS128 Centrale Sarda tratto chiuso causa veicolo fermo da Gavoi a Sarule",
    "end": "/Date(1607027877344)/",
    "icon": 1,
    "incidentId": 9287597512058000,
    "isEndTimeBackfilled": true,
    "lastModified": "/Date(1606992515752)/",
    "roadClosed": true,
    "severity": 4,
    "source": 5,
    "start": "/Date(1606972740000)/",
    "title": "SS128 / Strada Statale Numero 128 NB",
    "toPoint": {
      "type": "Point",
      "coordinates": [
        40.185309,
        9.18435
      ]
    },
    "type": 3,
    "verified": true
  }
]
